snapwell/__init__.py
snapwell/snapconfig.py
snapwell/snapecl.py
snapwell/snapwell_main.py
snapwell/version.py
snapwell/wellpath.py
snapwell/_ert_hooks/SNAPWELL
snapwell/_ert_hooks/__init__.py
snapwell/_ert_hooks/_ert_hook.py
snapwell-2.0.1.dist-info/LICENSE
snapwell-2.0.1.dist-info/METADATA
snapwell-2.0.1.dist-info/WHEEL
snapwell-2.0.1.dist-info/entry_points.txt
snapwell-2.0.1.dist-info/top_level.txt
snapwell-2.0.1.dist-info/RECORD
