Metadata-Version: 2.1
Name: snapwell
Version: 2.0.1
Summary: UNKNOWN
Home-page: UNKNOWN
License: GPL-3.0
Platform: any
Classifier: Development Status :: 1 - Planning
Classifier: Environment :: Plugins
Classifier: Intended Audience :: Developers
Classifier: Intended Audience :: Science/Research
Classifier: License :: OSI Approved :: GNU General Public License v3 or later (GPLv3+)
Classifier: Natural Language :: English
Classifier: Programming Language :: Python
Classifier: Programming Language :: Python :: 3.6
Classifier: Programming Language :: Python :: 3.7
Classifier: Programming Language :: Python :: 3.8
Classifier: Topic :: Scientific/Engineering
Classifier: Topic :: Software Development :: Libraries :: Python Modules
Requires-Dist: libecl
Requires-Dist: pydantic
Requires-Dist: typing-extensions
Requires-Dist: dataclasses (>=0.6) ; python_version < "3.7"
